[
  {
    "Uid": "N01_Y1_NPV",
    "Year": "Year 1",
    "Strand": "Number and place value",
    "Substrand": "counting (in multiples)",
    "Ref": "N1",
    "Module": "count to and across 100, forwards and backwards, beginning with 0 or 1, or from any given number; count in multiples of twos, fives and tens"
  },
  {
    "Uid": "N01_Y2_NPV",
    "Year": "Year 2",
    "Strand": "Number and place value",
    "Substrand": "counting (in multiples)",
    "Ref": "N1",
    "Module": "count in steps of 2, 3, and 5 from 0, and in tens from any number, forward or backward"
  },
  {
    "Uid": "N01_Y3_NPV",
    "Year": "Year 3",
    "Strand": "Number and place value",
    "Substrand": "counting (in multiples)",
    "Ref": "N1",
    "Module": "count from 0 in multiples of 4, 8, 50 and 100"
  },
  {
    "Uid": "N01_Y4_NPV",
    "Year": "Year 4",
    "Strand": "Number and place value",
    "Substrand": "counting (in multiples)",
    "Ref": "N1",
    "Module": "count in multiples of 6, 7, 9, 25 and 1,000"
  },
  {
    "Uid": "N01_Y5_NPV",
    "Year": "Year 5",
    "Strand": "Number and place value",
    "Substrand": "counting (in multiples)",
    "Ref": "N1",
    "Module": "count forwards or backwards in steps of powers of 10 for any given number up to 1,000,000"
  },
  {
    "Uid": "N01_Y6_NPV",
    "Year": "Year 6",
    "Strand": "Number and place value",
    "Substrand": "counting (in multiples)",
    "Ref": "N1",
    "Module": ""
  },
  {
    "Uid": "N02_Y1_NPV",
    "Year": "Year 1",
    "Strand": "Number and place value",
    "Substrand": "read, write, order and compare numbers",
    "Ref": "N2",
    "Module": "count, read and write numbers to 100 in numerals; given a number, identify one more and one less; read and write numbers from 1 to 20 in numerals and words"
  },
  {
    "Uid": "N02_Y2_NPV",
    "Year": "Year 2",
    "Strand": "Number and place value",
    "Substrand": "read, write, order and compare numbers",
    "Ref": "N2",
    "Module": "read and write numbers to at least 100 in numerals and in words; compare and order numbers from 0 up to 100; use <, > and = signs"
  },
  {
    "Uid": "N02_Y3_NPV",
    "Year": "Year 3",
    "Strand": "Number and place value",
    "Substrand": "read, write, order and compare numbers",
    "Ref": "N2",
    "Module": "compare and order numbers up to 1,000; read and write numbers to 1,000 in numerals and in words; find 10 or 100 more or less than a given number"
  },
  {
    "Uid": "N02_Y4_NPV",
    "Year": "Year 4",
    "Strand": "Number and place value",
    "Substrand": "read, write, order and compare numbers",
    "Ref": "N2",
    "Module": "order and compare numbers beyond 1,000; find 1,000 more or less than a given number"
  },
  {
    "Uid": "N02_Y5_NPV",
    "Year": "Year 5",
    "Strand": "Number and place value",
    "Substrand": "read, write, order and compare numbers",
    "Ref": "N2",
    "Module": "read, write, order and compare numbers to at least 1,000,000"
  },
  {
    "Uid": "N02_Y6_NPV",
    "Year": "Year 6",
    "Strand": "Number and place value",
    "Substrand": "read, write, order and compare numbers",
    "Ref": "N2",
    "Module": "read, write, order and compare numbers up to 10,000,000"
  },
  {
    "Uid": "N03_Y1_NPV",
    "Year": "Year 1",
    "Strand": "Number and place value",
    "Substrand": "place value; roman numerals",
    "Ref": "N3",
    "Module": ""
  },
  {
    "Uid": "N03_Y2_NPV",
    "Year": "Year 2",
    "Strand": "Number and place value",
    "Substrand": "place value; roman numerals",
    "Ref": "N3",
    "Module": "recognise the place value of each digit in a two-digit number (tens, ones)"
  },
  {
    "Uid": "N03_Y3_NPV",
    "Year": "Year 3",
    "Strand": "Number and place value",
    "Substrand": "place value; roman numerals",
    "Ref": "N3",
    "Module": "recognise the place value of each digit in a three-digit number (hundreds, tens, ones)"
  },
  {
    "Uid": "N03_Y4_NPV",
    "Year": "Year 4",
    "Strand": "Number and place value",
    "Substrand": "place value; roman numerals",
    "Ref": "N3",
    "Module": "recognise the place value of each digit in a four-digit number (thousands, hundreds, tens and ones); read Roman numerals to 100 (I to C) and know that over time, the numeral system changed to include the concept of zero and place value"
  },
  {
    "Uid": "N03_Y5_NPV",
    "Year": "Year 5",
    "Strand": "Number and place value",
    "Substrand": "place value; roman numerals",
    "Ref": "N3",
    "Module": "determine the value of each digit in numbers up to 1,000,000; read Roman numerals to 1,000 (M) and recognise years written in Roman numerals"
  },
  {
    "Uid": "N03_Y6_NPV",
    "Year": "Year 6",
    "Strand": "Number and place value",
    "Substrand": "place value; roman numerals",
    "Ref": "N3",
    "Module": "determine the value of each digit in numbers up to 10,000,000"
  },
  {
    "Uid": "N04_Y1_NPV",
    "Year": "Year 1",
    "Strand": "Number and place value",
    "Substrand": "identify, represent and estimate; rounding",
    "Ref": "N4",
    "Module": "identify and represent numbers using objects and pictorial representations including the number line, and use the language of: equal to, more than, less than (fewer), most, least"
  },
  {
    "Uid": "N04_Y2_NPV",
    "Year": "Year 2",
    "Strand": "Number and place value",
    "Substrand": "identify, represent and estimate; rounding",
    "Ref": "N4",
    "Module": "identify, represent and estimate numbers using different representations, including the number line"
  },
  {
    "Uid": "N04_Y3_NPV",
    "Year": "Year 3",
    "Strand": "Number and place value",
    "Substrand": "identify, represent and estimate; rounding",
    "Ref": "N4",
    "Module": "identify, represent and estimate numbers using different representations"
  },
  {
    "Uid": "N04_Y4_NPV",
    "Year": "Year 4",
    "Strand": "Number and place value",
    "Substrand": "identify, represent and estimate; rounding",
    "Ref": "N4",
    "Module": "identify, represent and estimate numbers using different representations; round any number to the nearest 10, 100 or 1,000"
  },
  {
    "Uid": "N04_Y5_NPV",
    "Year": "Year 5",
    "Strand": "Number and place value",
    "Substrand": "identify, represent and estimate; rounding",
    "Ref": "N4",
    "Module": "round any number up to 1,000,000 to the nearest 10, 100, 1,000, 10,000 and 100,000"
  },
  {
    "Uid": "N04_Y6_NPV",
    "Year": "Year 6",
    "Strand": "Number and place value",
    "Substrand": "identify, represent and estimate; rounding",
    "Ref": "N4",
    "Module": "round any whole number to a required degree of accuracy"
  },
  {
    "Uid": "N05_Y1_NPV",
    "Year": "Year 1",
    "Strand": "Number and place value",
    "Substrand": "negative numbers",
    "Ref": "N5",
    "Module": ""
  },
  {
    "Uid": "N05_Y2_NPV",
    "Year": "Year 2",
    "Strand": "Number and place value",
    "Substrand": "negative numbers",
    "Ref": "N5",
    "Module": ""
  },
  {
    "Uid": "N05_Y3_NPV",
    "Year": "Year 3",
    "Strand": "Number and place value",
    "Substrand": "negative numbers",
    "Ref": "N5",
    "Module": ""
  },
  {
    "Uid": "N05_Y4_NPV",
    "Year": "Year 4",
    "Strand": "Number and place value",
    "Substrand": "negative numbers",
    "Ref": "N5",
    "Module": "count backwards through zero to include negative numbers"
  },
  {
    "Uid": "N05_Y5_NPV",
    "Year": "Year 5",
    "Strand": "Number and place value",
    "Substrand": "negative numbers",
    "Ref": "N5",
    "Module": "interpret negative numbers in context, count forwards and backwards with positive and negative whole numbers, including through zero"
  },
  {
    "Uid": "N05_Y6_NPV",
    "Year": "Year 6",
    "Strand": "Number and place value",
    "Substrand": "negative numbers",
    "Ref": "N5",
    "Module": "use negative numbers in context, and calculate intervals across zero"
  },
  {
    "Uid": "N06_Y1_NPV",
    "Year": "Year 1",
    "Strand": "Number and place value",
    "Substrand": "number problems",
    "Ref": "N6",
    "Module": ""
  },
  {
    "Uid": "N06_Y2_NPV",
    "Year": "Year 2",
    "Strand": "Number and place value",
    "Substrand": "number problems",
    "Ref": "N6",
    "Module": "use place value and number facts to solve problems"
  },
  {
    "Uid": "N06_Y3_NPV",
    "Year": "Year 3",
    "Strand": "Number and place value",
    "Substrand": "number problems",
    "Ref": "N6",
    "Module": "solve number problems and practical problems involving 3N1-3N4"
  },
  {
    "Uid": "N06_Y4_NPV",
    "Year": "Year 4",
    "Strand": "Number and place value",
    "Substrand": "number problems",
    "Ref": "N6",
    "Module": "solve number and practical problems that involve 4N1-4N5 and with increasingly large positive numbers"
  },
  {
    "Uid": "N06_Y5_NPV",
    "Year": "Year 5",
    "Strand": "Number and place value",
    "Substrand": "number problems",
    "Ref": "N6",
    "Module": "solve number problems and practical problems that involve 5N1-5N5"
  },
  {
    "Uid": "N06_Y6_NPV",
    "Year": "Year 6",
    "Strand": "Number and place value",
    "Substrand": "number problems",
    "Ref": "N6",
    "Module": "solve number problems and practical problems that involve 6N2-6N5"
  },
  {
    "Uid": "C01_Y1_CALC",
    "Year": "Year 1",
    "Strand": "Addition, subtraction, multiplication and division (calculations)",
    "Substrand": "add / subtract mentally",
    "Ref": "C1",
    "Module": "represent and use number bonds and related subtraction facts within 20"
  },
  {
    "Uid": "C01_Y2_CALC",
    "Year": "Year 2",
    "Strand": "Addition, subtraction, multiplication and division (calculations)",
    "Substrand": "add / subtract mentally",
    "Ref": "C1",
    "Module": "recall and use addition and subtraction facts to 20 fluently, and derive and use related facts up to 100"
  },
  {
    "Uid": "C01_Y3_CALC",
    "Year": "Year 3",
    "Strand": "Addition, subtraction, multiplication and division (calculations)",
    "Substrand": "add / subtract mentally",
    "Ref": "C1",
    "Module": "add and subtract numbers mentally, including: a three-digit number and ones, a three-digit number and tens, a three-digit number and hundreds"
  },
  {
    "Uid": "C01_Y4_CALC",
    "Year": "Year 4",
    "Strand": "Addition, subtraction, multiplication and division (calculations)",
    "Substrand": "add / subtract mentally",
    "Ref": "C1",
    "Module": ""
  },
  {
    "Uid": "C01_Y5_CALC",
    "Year": "Year 5",
    "Strand": "Addition, subtraction, multiplication and division (calculations)",
    "Substrand": "add / subtract mentally",
    "Ref": "C1",
    "Module": "add and subtract numbers mentally with increasingly large numbers"
  },
  {
    "Uid": "C01_Y6_CALC",
    "Year": "Year 6",
    "Strand": "Addition, subtraction, multiplication and division (calculations)",
    "Substrand": "add / subtract mentally",
    "Ref": "C1",
    "Module": ""
  },
  {
    "Uid": "C02_Y1_CALC",
    "Year": "Year 1",
    "Strand": "Addition, subtraction, multiplication and division (calculations)",
    "Substrand": "add / subtract using written methods",
    "Ref": "C2",
    "Module": "add and subtract one-digit and two-digit numbers to 20, including zero; read, write and interpret mathematical statements involving addition (+), subtraction (–) and equals (=) signs"
  },
  {
    "Uid": "C02_Y2_CALC",
    "Year": "Year 2",
    "Strand": "Addition, subtraction, multiplication and division (calculations)",
    "Substrand": "add / subtract using written methods",
    "Ref": "C2",
    "Module": "add and subtract numbers using concrete objects, pictorial representations, and mentally, including: a two-digit number and ones, a two-digit number and tens, two two-digit numbers, adding three one-digit numbers"
  },
  {
    "Uid": "C02_Y3_CALC",
    "Year": "Year 3",
    "Strand": "Addition, subtraction, multiplication and division (calculations)",
    "Substrand": "add / subtract using written methods",
    "Ref": "C2",
    "Module": "add and subtract numbers with up to three digits, using formal written methods of columnar addition and subtraction"
  },
  {
    "Uid": "C02_Y4_CALC",
    "Year": "Year 4",
    "Strand": "Addition, subtraction, multiplication and division (calculations)",
    "Substrand": "add / subtract using written methods",
    "Ref": "C2",
    "Module": "add and subtract numbers with up to 4 digits using the formal written methods of columnar addition and subtraction where appropriate"
  },
  {
    "Uid": "C02_Y5_CALC",
    "Year": "Year 5",
    "Strand": "Addition, subtraction, multiplication and division (calculations)",
    "Substrand": "add / subtract using written methods",
    "Ref": "C2",
    "Module": "add and subtract whole numbers with more than 4 digits, including using formal written methods (columnar addition and subtraction)"
  },
  {
    "Uid": "C02_Y6_CALC",
    "Year": "Year 6",
    "Strand": "Addition, subtraction, multiplication and division (calculations)",
    "Substrand": "add / subtract using written methods",
    "Ref": "C2",
    "Module": ""
  },
  {
    "Uid": "C03_Y1_CALC",
    "Year": "Year 1",
    "Strand": "Addition, subtraction, multiplication and division (calculations)",
    "Substrand": "estimate, use inverses and check",
    "Ref": "C3",
    "Module": ""
  },
  {
    "Uid": "C03_Y2_CALC",
    "Year": "Year 2",
    "Strand": "Addition, subtraction, multiplication and division (calculations)",
    "Substrand": "estimate, use inverses and check",
    "Ref": "C3",
    "Module": "recognise and use the inverse relationship between addition and subtraction and use this to check calculations and missing number problems"
  },
  {
    "Uid": "C03_Y3_CALC",
    "Year": "Year 3",
    "Strand": "Addition, subtraction, multiplication and division (calculations)",
    "Substrand": "estimate, use inverses and check",
    "Ref": "C3",
    "Module": "estimate the answer to a calculation and use inverse operations to check answers"
  },
  {
    "Uid": "C03_Y4_CALC",
    "Year": "Year 4",
    "Strand": "Addition, subtraction, multiplication and division (calculations)",
    "Substrand": "estimate, use inverses and check",
    "Ref": "C3",
    "Module": "estimate and use inverse operations to check answers to a calculation"
  },
  {
    "Uid": "C03_Y5_CALC",
    "Year": "Year 5",
    "Strand": "Addition, subtraction, multiplication and division (calculations)",
    "Substrand": "estimate, use inverses and check",
    "Ref": "C3",
    "Module": "use rounding to check answers to calculations and determine, in the context of a problem, levels of accuracy"
  },
  {
    "Uid": "C03_Y6_CALC",
    "Year": "Year 6",
    "Strand": "Addition, subtraction, multiplication and division (calculations)",
    "Substrand": "estimate, use inverses and check",
    "Ref": "C3",
    "Module": "use estimation to check answers to calculations and determine, in the context of a problem, an appropriate degree of accuracy"
  },
  {
    "Uid": "C04_Y1_CALC",
    "Year": "Year 1",
    "Strand": "Addition, subtraction, multiplication and division (calculations)",
    "Substrand": "add / subtract to solve problems",
    "Ref": "C4",
    "Module": "solve one-step problems that involve addition and subtraction, using concrete objects and pictorial representations, and missing number problems such as 7 = _ – 9"
  },
  {
    "Uid": "C04_Y2_CALC",
    "Year": "Year 2",
    "Strand": "Addition, subtraction, multiplication and division (calculations)",
    "Substrand": "add / subtract to solve problems",
    "Ref": "C4",
    "Module": "solve problems with addition and subtraction: using concrete objects and pictorial representations, including those involving numbers, quantities and measures; applying their increasing knowledge of mental and written methods"
  },
  {
    "Uid": "C04_Y3_CALC",
    "Year": "Year 3",
    "Strand": "Addition, subtraction, multiplication and division (calculations)",
    "Substrand": "add / subtract to solve problems",
    "Ref": "C4",
    "Module": "solve problems, including missing number problems, using number facts, place value, and more complex addition and subtraction"
  },
  {
    "Uid": "C04_Y4_CALC",
    "Year": "Year 4",
    "Strand": "Addition, subtraction, multiplication and division (calculations)",
    "Substrand": "add / subtract to solve problems",
    "Ref": "C4",
    "Module": "solve addition and subtraction two-step problems in contexts, deciding which operations and methods to use and why"
  },
  {
    "Uid": "C04_Y5_CALC",
    "Year": "Year 5",
    "Strand": "Addition, subtraction, multiplication and division (calculations)",
    "Substrand": "add / subtract to solve problems",
    "Ref": "C4",
    "Module": "solve addition and subtraction multi-step problems in contexts, deciding which operations and methods to use and why"
  },
  {
    "Uid": "C04_Y6_CALC",
    "Year": "Year 6",
    "Strand": "Addition, subtraction, multiplication and division (calculations)",
    "Substrand": "add / subtract to solve problems",
    "Ref": "C4",
    "Module": "solve addition and subtraction multi-step problems in contexts, deciding which operations and methods to use and why"
  },
  {
    "Uid": "C05_Y1_CALC",
    "Year": "Year 1",
    "Strand": "Addition, subtraction, multiplication and division (calculations)",
    "Substrand": "properties of number (multiples, factors, primes, squares and cubes)",
    "Ref": "C5",
    "Module": ""
  },
  {
    "Uid": "C05_Y2_CALC",
    "Year": "Year 2",
    "Strand": "Addition, subtraction, multiplication and division (calculations)",
    "Substrand": "properties of number (multiples, factors, primes, squares and cubes)",
    "Ref": "C5",
    "Module": ""
  },
  {
    "Uid": "C05_Y3_CALC",
    "Year": "Year 3",
    "Strand": "Addition, subtraction, multiplication and division (calculations)",
    "Substrand": "properties of number (multiples, factors, primes, squares and cubes)",
    "Ref": "C5",
    "Module": ""
  },
  {
    "Uid": "C05_Y4_CALC",
    "Year": "Year 4",
    "Strand": "Addition, subtraction, multiplication and division (calculations)",
    "Substrand": "properties of number (multiples, factors, primes, squares and cubes)",
    "Ref": "C5",
    "Module": ""
  },
  {
    "Uid": "C05_Y5_CALC",
    "Year": "Year 5",
    "Strand": "Addition, subtraction, multiplication and division (calculations)",
    "Substrand": "properties of number (multiples, factors, primes, squares and cubes)",
    "Ref": "C5",
    "Module": "identify multiples and factors, including finding all factor pairs of a number and common factors of two numbers; know and use the vocabulary of prime numbers, prime factors and composite (non-prime) numbers; establish whether a number up to 100 is prime and recall prime numbers up to 19; recognise and use square numbers and cube numbers, and the notation for squared (²) and cubed (³)"
  },
  {
    "Uid": "C05_Y6_CALC",
    "Year": "Year 6",
    "Strand": "Addition, subtraction, multiplication and division (calculations)",
    "Substrand": "properties of number (multiples, factors, primes, squares and cubes)",
    "Ref": "C5",
    "Module": "identify common factors, common multiples and prime numbers"
  },
  {
    "Uid": "C06_Y1_CALC",
    "Year": "Year 1",
    "Strand": "Addition, subtraction, multiplication and division (calculations)",
    "Substrand": "multiply / divide mentally",
    "Ref": "C6",
    "Module": ""
  },
  {
    "Uid": "C06_Y2_CALC",
    "Year": "Year 2",
    "Strand": "Addition, subtraction, multiplication and division (calculations)",
    "Substrand": "multiply / divide mentally",
    "Ref": "C6",
    "Module": "recall and use multiplication and division facts for the 2, 5 and 10 multiplication tables, including recognising odd and even numbers"
  },
  {
    "Uid": "C06_Y3_CALC",
    "Year": "Year 3",
    "Strand": "Addition, subtraction, multiplication and division (calculations)",
    "Substrand": "multiply / divide mentally",
    "Ref": "C6",
    "Module": "recall and use multiplication and division facts for the 3, 4 and 8 multiplication tables"
  },
  {
    "Uid": "C06_Y4_CALC",
    "Year": "Year 4",
    "Strand": "Addition, subtraction, multiplication and division (calculations)",
    "Substrand": "multiply / divide mentally",
    "Ref": "C6",
    "Module": "recall multiplication and division facts for multiplication tables up to 12 x 12; use place value, known and derived facts to multiply and divide mentally, including: multiplying by 0 and 1, dividing by 1, multiplying together three numbers; recognise and use factor pairs and commutativity in mental calculations"
  },
  {
    "Uid": "C06_Y5_CALC",
    "Year": "Year 5",
    "Strand": "Addition, subtraction, multiplication and division (calculations)",
    "Substrand": "multiply / divide mentally",
    "Ref": "C6",
    "Module": "multiply and divide numbers mentally drawing upon known facts; multiply and divide whole numbers and those involving decimals by 10, 100 and 1,000"
  },
  {
    "Uid": "C06_Y6_CALC",
    "Year": "Year 6",
    "Strand": "Addition, subtraction, multiplication and division (calculations)",
    "Substrand": "multiply / divide mentally",
    "Ref": "C6",
    "Module": "perform mental calculations, including with mixed operations and large numbers"
  },
  {
    "Uid": "C07_Y1_CALC",
    "Year": "Year 1",
    "Strand": "Addition, subtraction, multiplication and division (calculations)",
    "Substrand": "multiply / divide using written methods",
    "Ref": "C7",
    "Module": ""
  },
  {
    "Uid": "C07_Y2_CALC",
    "Year": "Year 2",
    "Strand": "Addition, subtraction, multiplication and division (calculations)",
    "Substrand": "multiply / divide using written methods",
    "Ref": "C7",
    "Module": "calculate mathematical statements for multiplication and division within the multiplication tables and write them using the multiplication (×), division (÷) and equals (=) signs"
  },
  {
    "Uid": "C07_Y3_CALC",
    "Year": "Year 3",
    "Strand": "Addition, subtraction, multiplication and division (calculations)",
    "Substrand": "multiply / divide using written methods",
    "Ref": "C7",
    "Module": "write and calculate mathematical statements for multiplication and division using the multiplication tables that pupils know, including for two-digit numbers times one-digit numbers, using mental and progressing to formal written methods"
  },
  {
    "Uid": "C07_Y4_CALC",
    "Year": "Year 4",
    "Strand": "Addition, subtraction, multiplication and division (calculations)",
    "Substrand": "multiply / divide using written methods",
    "Ref": "C7",
    "Module": "multiply two-digit and three-digit numbers by a one-digit number using formal written layout"
  },
  {
    "Uid": "C07_Y5_CALC",
    "Year": "Year 5",
    "Strand": "Addition, subtraction, multiplication and division (calculations)",
    "Substrand": "multiply / divide using written methods",
    "Ref": "C7",
    "Module": "multiply numbers up to 4 digits by a one- or two-digit number using a formal written method, including long multiplication for two-digit numbers; divide numbers up to 4 digits by a one-digit number using the formal written method of short division and interpret remainders appropriately for the context"
  },
  {
    "Uid": "C07_Y6_CALC",
    "Year": "Year 6",
    "Strand": "Addition, subtraction, multiplication and division (calculations)",
    "Substrand": "multiply / divide using written methods",
    "Ref": "C7",
    "Module": "multiply multi-digit numbers up to 4 digits by a two-digit whole number using the formal written method of long multiplication; divide numbers up to 4 digits by a two-digit whole number using the formal written method of long division, and interpret remainders as whole number remainders, fractions, or by rounding, as appropriate for the context; divide numbers up to 4 digits by a two-digit number using the formal written method of short division where appropriate, interpreting remainders according to the context"
  },
  {
    "Uid": "C08_Y1_CALC",
    "Year": "Year 1",
    "Strand": "Addition, subtraction, multiplication and division (calculations)",
    "Substrand": "solve problems (commutative, associative, distributive and all four operations)",
    "Ref": "C8",
    "Module": "solve one-step problems involving multiplication and division, by calculating the answer using concrete objects, pictorial representations and arrays with the support of the teacher"
  },
  {
    "Uid": "C08_Y2_CALC",
    "Year": "Year 2",
    "Strand": "Addition, subtraction, multiplication and division (calculations)",
    "Substrand": "solve problems (commutative, associative, distributive and all four operations)",
    "Ref": "C8",
    "Module": "solve problems involving multiplication and division, using materials, arrays, repeated addition, mental methods, and multiplication and division facts, including problems in contexts; show that addition of two numbers can be done in any order (commutative) and subtraction of one number from another cannot; show that multiplication of two numbers can be done in any order (commutative) and division of one number by another cannot"
  },
  {
    "Uid": "C08_Y3_CALC",
    "Year": "Year 3",
    "Strand": "Addition, subtraction, multiplication and division (calculations)",
    "Substrand": "solve problems (commutative, associative, distributive and all four operations)",
    "Ref": "C8",
    "Module": "solve problems, including missing number problems, involving multiplication and division, including integer scaling problems and correspondence problems in which n objects are connected to m objects"
  },
  {
    "Uid": "C08_Y4_CALC",
    "Year": "Year 4",
    "Strand": "Addition, subtraction, multiplication and division (calculations)",
    "Substrand": "solve problems (commutative, associative, distributive and all four operations)",
    "Ref": "C8",
    "Module": "solve problems involving multiplying and adding, including using the distributive law to multiply two-digit numbers by one digit, integer scaling problems and harder correspondence problems such as n objects are connected to m objects"
  },
  {
    "Uid": "C08_Y5_CALC",
    "Year": "Year 5",
    "Strand": "Addition, subtraction, multiplication and division (calculations)",
    "Substrand": "solve problems (commutative, associative, distributive and all four operations)",
    "Ref": "C8",
    "Module": "solve problems involving multiplication and division including using their knowledge of factors and multiples, squares and cubes; solve problems involving addition, subtraction, multiplication and division and a combination of these, including understanding the meaning of the equals sign; solve problems involving multiplication and division including scaling by simple fractions and problems involving simple rates"
  },
  {
    "Uid": "C08_Y6_CALC",
    "Year": "Year 6",
    "Strand": "Addition, subtraction, multiplication and division (calculations)",
    "Substrand": "solve problems (commutative, associative, distributive and all four operations)",
    "Ref": "C8",
    "Module": "solve problems involving addition, subtraction, multiplication and division"
  },
  {
    "Uid": "C09_Y1_CALC",
    "Year": "Year 1",
    "Strand": "Addition, subtraction, multiplication and division (calculations)",
    "Substrand": "order of operations",
    "Ref": "C9",
    "Module": ""
  },
  {
    "Uid": "C09_Y2_CALC",
    "Year": "Year 2",
    "Strand": "Addition, subtraction, multiplication and division (calculations)",
    "Substrand": "order of operations",
    "Ref": "C9",
    "Module": ""
  },
  {
    "Uid": "C09_Y3_CALC",
    "Year": "Year 3",
    "Strand": "Addition, subtraction, multiplication and division (calculations)",
    "Substrand": "order of operations",
    "Ref": "C9",
    "Module": ""
  },
  {
    "Uid": "C09_Y4_CALC",
    "Year": "Year 4",
    "Strand": "Addition, subtraction, multiplication and division (calculations)",
    "Substrand": "order of operations",
    "Ref": "C9",
    "Module": ""
  },
  {
    "Uid": "C09_Y5_CALC",
    "Year": "Year 5",
    "Strand": "Addition, subtraction, multiplication and division (calculations)",
    "Substrand": "order of operations",
    "Ref": "C9",
    "Module": ""
  },
  {
    "Uid": "C09_Y6_CALC",
    "Year": "Year 6",
    "Strand": "Addition, subtraction, multiplication and division (calculations)",
    "Substrand": "order of operations",
    "Ref": "C9",
    "Module": "use their knowledge of the order of operations to carry out calculations involving the four operations"
  },
  {
    "Uid": "F01_Y1_FRAC",
    "Year": "Year 1",
    "Strand": "Fractions, decimals and percentages",
    "Substrand": "recognise, find, write, name and count fractions",
    "Ref": "F1",
    "Module": "recognise, find and name a half as one of two equal parts of an object, shape or quantity; recognise, find and name a quarter as one of four equal parts of an object, shape or quantity"
  },
  {
    "Uid": "F01_Y2_FRAC",
    "Year": "Year 2",
    "Strand": "Fractions, decimals and percentages",
    "Substrand": "recognise, find, write, name and count fractions",
    "Ref": "F1",
    "Module": "recognise, find, name and write fractions ⅓, ¼, ²⁄₄ and ¾ of a length, shape, set of objects or quantity; write simple fractions, for example, ½ of 6 = 3"
  },
  {
    "Uid": "F01_Y3_FRAC",
    "Year": "Year 3",
    "Strand": "Fractions, decimals and percentages",
    "Substrand": "recognise, find, write, name and count fractions",
    "Ref": "F1",
    "Module": "count up and down in tenths, recognise that tenths arise from dividing an object into 10 equal parts and in dividing one-digit numbers or quantities by 10; recognise, find and write fractions of a discrete set of objects: unit fractions and non-unit fractions with small denominators; recognise and use fractions as numbers: unit fractions and non-unit fractions with small denominators"
  },
  {
    "Uid": "F01_Y4_FRAC",
    "Year": "Year 4",
    "Strand": "Fractions, decimals and percentages",
    "Substrand": "recognise, find, write, name and count fractions",
    "Ref": "F1",
    "Module": "count up and down in hundredths; recognise that hundredths arise when dividing an object by a hundred and dividing tenths by ten"
  },
  {
    "Uid": "F01_Y5_FRAC",
    "Year": "Year 5",
    "Strand": "Fractions, decimals and percentages",
    "Substrand": "recognise, find, write, name and count fractions",
    "Ref": "F1",
    "Module": ""
  },
  {
    "Uid": "F01_Y6_FRAC",
    "Year": "Year 6",
    "Strand": "Fractions, decimals and percentages",
    "Substrand": "recognise, find, write, name and count fractions",
    "Ref": "F1",
    "Module": ""
  },
  {
    "Uid": "F02_Y1_FRAC",
    "Year": "Year 1",
    "Strand": "Fractions, decimals and percentages",
    "Substrand": "equivalent fractions",
    "Ref": "F2",
    "Module": ""
  },
  {
    "Uid": "F02_Y2_FRAC",
    "Year": "Year 2",
    "Strand": "Fractions, decimals and percentages",
    "Substrand": "equivalent fractions",
    "Ref": "F2",
    "Module": "recognise the equivalence of ²⁄₄ and ½"
  },
  {
    "Uid": "F02_Y3_FRAC",
    "Year": "Year 3",
    "Strand": "Fractions, decimals and percentages",
    "Substrand": "equivalent fractions",
    "Ref": "F2",
    "Module": "recognise and show, using diagrams, equivalent fractions with small denominators"
  },
  {
    "Uid": "F02_Y4_FRAC",
    "Year": "Year 4",
    "Strand": "Fractions, decimals and percentages",
    "Substrand": "equivalent fractions",
    "Ref": "F2",
    "Module": "recognise and show, using diagrams, families of common equivalent fractions"
  },
  {
    "Uid": "F02_Y5_FRAC",
    "Year": "Year 5",
    "Strand": "Fractions, decimals and percentages",
    "Substrand": "equivalent fractions",
    "Ref": "F2",
    "Module": "recognise mixed numbers and improper fractions and convert from one form to the other; write mathematical statements >1 as a mixed number [e.g. ⅖ + ⅘ = ⁶⁄₅ = 1⅕]; identify name and write equivalent fractions of a given fraction, represented visually, including tenths and hundredths"
  },
  {
    "Uid": "F02_Y6_FRAC",
    "Year": "Year 6",
    "Strand": "Fractions, decimals and percentages",
    "Substrand": "equivalent fractions",
    "Ref": "F2",
    "Module": "use common factors to simplify fractions; use common multiples to express fractions in the same denomination"
  },
  {
    "Uid": "F03_Y1_FRAC",
    "Year": "Year 1",
    "Strand": "Fractions, decimals and percentages",
    "Substrand": "comparing and ordering fractions",
    "Ref": "F3",
    "Module": ""
  },
  {
    "Uid": "F03_Y2_FRAC",
    "Year": "Year 2",
    "Strand": "Fractions, decimals and percentages",
    "Substrand": "comparing and ordering fractions",
    "Ref": "F3",
    "Module": ""
  },
  {
    "Uid": "F03_Y3_FRAC",
    "Year": "Year 3",
    "Strand": "Fractions, decimals and percentages",
    "Substrand": "comparing and ordering fractions",
    "Ref": "F3",
    "Module": "compare and order unit fractions and fractions with the same denominators"
  },
  {
    "Uid": "F03_Y4_FRAC",
    "Year": "Year 4",
    "Strand": "Fractions, decimals and percentages",
    "Substrand": "comparing and ordering fractions",
    "Ref": "F3",
    "Module": ""
  },
  {
    "Uid": "F03_Y5_FRAC",
    "Year": "Year 5",
    "Strand": "Fractions, decimals and percentages",
    "Substrand": "comparing and ordering fractions",
    "Ref": "F3",
    "Module": "compare and order fractions whose denominators are all multiples of the same number"
  },
  {
    "Uid": "F03_Y6_FRAC",
    "Year": "Year 6",
    "Strand": "Fractions, decimals and percentages",
    "Substrand": "comparing and ordering fractions",
    "Ref": "F3",
    "Module": "compare and order fractions, including fractions > 1"
  },
  {
    "Uid": "F04_Y1_FRAC",
    "Year": "Year 1",
    "Strand": "Fractions, decimals and percentages",
    "Substrand": "add / subtract fractions",
    "Ref": "F4",
    "Module": ""
  },
  {
    "Uid": "F04_Y2_FRAC",
    "Year": "Year 2",
    "Strand": "Fractions, decimals and percentages",
    "Substrand": "add / subtract fractions",
    "Ref": "F4",
    "Module": ""
  },
  {
    "Uid": "F04_Y3_FRAC",
    "Year": "Year 3",
    "Strand": "Fractions, decimals and percentages",
    "Substrand": "add / subtract fractions",
    "Ref": "F4",
    "Module": "add and subtract fractions with the same denominator within one whole [e.g. ⅚ + ⅚ = ⁶⁄₇]"
  },
  {
    "Uid": "F04_Y4_FRAC",
    "Year": "Year 4",
    "Strand": "Fractions, decimals and percentages",
    "Substrand": "add / subtract fractions",
    "Ref": "F4",
    "Module": "add and subtract fractions with the same denominator"
  },
  {
    "Uid": "F04_Y5_FRAC",
    "Year": "Year 5",
    "Strand": "Fractions, decimals and percentages",
    "Substrand": "add / subtract fractions",
    "Ref": "F4",
    "Module": "add and subtract fractions with the same denominator and denominators that are multiples of the same number"
  },
  {
    "Uid": "F04_Y6_FRAC",
    "Year": "Year 6",
    "Strand": "Fractions, decimals and percentages",
    "Substrand": "add / subtract fractions",
    "Ref": "F4",
    "Module": "add and subtract fractions with different denominators and mixed numbers, using the concept of equivalent fractions"
  },
  {
    "Uid": "F05_Y1_FRAC",
    "Year": "Year 1",
    "Strand": "Fractions, decimals and percentages",
    "Substrand": "multiply / divide fractions",
    "Ref": "F5",
    "Module": ""
  },
  {
    "Uid": "F05_Y2_FRAC",
    "Year": "Year 2",
    "Strand": "Fractions, decimals and percentages",
    "Substrand": "multiply / divide fractions",
    "Ref": "F5",
    "Module": ""
  },
  {
    "Uid": "F05_Y3_FRAC",
    "Year": "Year 3",
    "Strand": "Fractions, decimals and percentages",
    "Substrand": "multiply / divide fractions",
    "Ref": "F5",
    "Module": ""
  },
  {
    "Uid": "F05_Y4_FRAC",
    "Year": "Year 4",
    "Strand": "Fractions, decimals and percentages",
    "Substrand": "multiply / divide fractions",
    "Ref": "F5",
    "Module": ""
  },
  {
    "Uid": "F05_Y5_FRAC",
    "Year": "Year 5",
    "Strand": "Fractions, decimals and percentages",
    "Substrand": "multiply / divide fractions",
    "Ref": "F5",
    "Module": "multiply proper fractions and mixed numbers by whole numbers, supported by materials and diagrams"
  },
  {
    "Uid": "F05_Y6_FRAC",
    "Year": "Year 6",
    "Strand": "Fractions, decimals and percentages",
    "Substrand": "multiply / divide fractions",
    "Ref": "F5",
    "Module": "multiply simple pairs of proper fractions, writing the answer in its simplest form [e.g. ¼ x ½ = ⅛]; divide proper fractions by whole numbers [e.g. ⅓ ÷ 2 = ⅙]"
  },
  {
    "Uid": "F06_Y1_FRAC",
    "Year": "Year 1",
    "Strand": "Fractions, decimals and percentages",
    "Substrand": "fractions / decimals equivalence",
    "Ref": "F6",
    "Module": ""
  },
  {
    "Uid": "F06_Y2_FRAC",
    "Year": "Year 2",
    "Strand": "Fractions, decimals and percentages",
    "Substrand": "fractions / decimals equivalence",
    "Ref": "F6",
    "Module": ""
  },
  {
    "Uid": "F06_Y3_FRAC",
    "Year": "Year 3",
    "Strand": "Fractions, decimals and percentages",
    "Substrand": "fractions / decimals equivalence",
    "Ref": "F6",
    "Module": ""
  },
  {
    "Uid": "F06_Y4_FRAC",
    "Year": "Year 4",
    "Strand": "Fractions, decimals and percentages",
    "Substrand": "fractions / decimals equivalence",
    "Ref": "F6",
    "Module": "recognise and write decimal equivalents to ¼, ½, ¾; recognise and write decimal equivalents of any number of tenths or hundredths"
  },
  {
    "Uid": "F06_Y5_FRAC",
    "Year": "Year 5",
    "Strand": "Fractions, decimals and percentages",
    "Substrand": "fractions / decimals equivalence",
    "Ref": "F6",
    "Module": "read and write decimal numbers as fractions [e.g. 0.71 = ⁷¹⁄₁₀₀]; recognise and use thousandths and relate them to tenths, hundredths and decimal equivalents"
  },
  {
    "Uid": "F06_Y6_FRAC",
    "Year": "Year 6",
    "Strand": "Fractions, decimals and percentages",
    "Substrand": "fractions / decimals equivalence",
    "Ref": "F6",
    "Module": "associate a fraction with division to calculate decimal fraction equivalents (e.g. 0.375) for a simple fraction [e.g. ⅜]"
  },
  {
    "Uid": "F07_Y1_FRAC",
    "Year": "Year 1",
    "Strand": "Fractions, decimals and percentages",
    "Substrand": "rounding decimals",
    "Ref": "F7",
    "Module": ""
  },
  {
    "Uid": "F07_Y2_FRAC",
    "Year": "Year 2",
    "Strand": "Fractions, decimals and percentages",
    "Substrand": "rounding decimals",
    "Ref": "F7",
    "Module": ""
  },
  {
    "Uid": "F07_Y3_FRAC",
    "Year": "Year 3",
    "Strand": "Fractions, decimals and percentages",
    "Substrand": "rounding decimals",
    "Ref": "F7",
    "Module": ""
  },
  {
    "Uid": "F07_Y4_FRAC",
    "Year": "Year 4",
    "Strand": "Fractions, decimals and percentages",
    "Substrand": "rounding decimals",
    "Ref": "F7",
    "Module": "round decimals with one decimal place to the nearest whole number"
  },
  {
    "Uid": "F07_Y5_FRAC",
    "Year": "Year 5",
    "Strand": "Fractions, decimals and percentages",
    "Substrand": "rounding decimals",
    "Ref": "F7",
    "Module": "round decimals with two decimal places to the nearest whole number and to one decimal place"
  },
  {
    "Uid": "F07_Y6_FRAC",
    "Year": "Year 6",
    "Strand": "Fractions, decimals and percentages",
    "Substrand": "rounding decimals",
    "Ref": "F7",
    "Module": ""
  },
  {
    "Uid": "F08_Y1_FRAC",
    "Year": "Year 1",
    "Strand": "Fractions, decimals and percentages",
    "Substrand": "compare and order decimals",
    "Ref": "F8",
    "Module": ""
  },
  {
    "Uid": "F08_Y2_FRAC",
    "Year": "Year 2",
    "Strand": "Fractions, decimals and percentages",
    "Substrand": "compare and order decimals",
    "Ref": "F8",
    "Module": ""
  },
  {
    "Uid": "F08_Y3_FRAC",
    "Year": "Year 3",
    "Strand": "Fractions, decimals and percentages",
    "Substrand": "compare and order decimals",
    "Ref": "F8",
    "Module": ""
  },
  {
    "Uid": "F08_Y4_FRAC",
    "Year": "Year 4",
    "Strand": "Fractions, decimals and percentages",
    "Substrand": "compare and order decimals",
    "Ref": "F8",
    "Module": "compare numbers with the same number of decimal places up to two decimal places"
  },
  {
    "Uid": "F08_Y5_FRAC",
    "Year": "Year 5",
    "Strand": "Fractions, decimals and percentages",
    "Substrand": "compare and order decimals",
    "Ref": "F8",
    "Module": "read, write, order and compare numbers with up to three decimal places"
  },
  {
    "Uid": "F08_Y6_FRAC",
    "Year": "Year 6",
    "Strand": "Fractions, decimals and percentages",
    "Substrand": "compare and order decimals",
    "Ref": "F8",
    "Module": ""
  },
  {
    "Uid": "F09_Y1_FRAC",
    "Year": "Year 1",
    "Strand": "Fractions, decimals and percentages",
    "Substrand": "multiply / divide decimals",
    "Ref": "F9",
    "Module": ""
  },
  {
    "Uid": "F09_Y2_FRAC",
    "Year": "Year 2",
    "Strand": "Fractions, decimals and percentages",
    "Substrand": "multiply / divide decimals",
    "Ref": "F9",
    "Module": ""
  },
  {
    "Uid": "F09_Y3_FRAC",
    "Year": "Year 3",
    "Strand": "Fractions, decimals and percentages",
    "Substrand": "multiply / divide decimals",
    "Ref": "F9",
    "Module": ""
  },
  {
    "Uid": "F09_Y4_FRAC",
    "Year": "Year 4",
    "Strand": "Fractions, decimals and percentages",
    "Substrand": "multiply / divide decimals",
    "Ref": "F9",
    "Module": "find the effect of dividing a one- or two-digit number by 10 and 100, identifying the value of the digits in the answer as ones, tenths and hundredths"
  },
  {
    "Uid": "F09_Y5_FRAC",
    "Year": "Year 5",
    "Strand": "Fractions, decimals and percentages",
    "Substrand": "multiply / divide decimals",
    "Ref": "F9",
    "Module": ""
  },
  {
    "Uid": "F09_Y6_FRAC",
    "Year": "Year 6",
    "Strand": "Fractions, decimals and percentages",
    "Substrand": "multiply / divide decimals",
    "Ref": "F9",
    "Module": "identify the value of each digit to three decimal places and multiply and divide numbers by 10, 100 and 1,000 giving answers up to three decimal places; multiply one-digit numbers with up to two-decimal places by whole numbers; use written division methods in cases where the answer has up to two-decimal places"
  },
  {
    "Uid": "F10_Y1_FRAC",
    "Year": "Year 1",
    "Strand": "Fractions, decimals and percentages",
    "Substrand": "solve problems with fractions and decimals",
    "Ref": "F10",
    "Module": ""
  },
  {
    "Uid": "F10_Y2_FRAC",
    "Year": "Year 2",
    "Strand": "Fractions, decimals and percentages",
    "Substrand": "solve problems with fractions and decimals",
    "Ref": "F10",
    "Module": ""
  },
  {
    "Uid": "F10_Y3_FRAC",
    "Year": "Year 3",
    "Strand": "Fractions, decimals and percentages",
    "Substrand": "solve problems with fractions and decimals",
    "Ref": "F10",
    "Module": "solve problems that involve 3F1-3F4"
  },
  {
    "Uid": "F10_Y4_FRAC",
    "Year": "Year 4",
    "Strand": "Fractions, decimals and percentages",
    "Substrand": "solve problems with fractions and decimals",
    "Ref": "F10",
    "Module": "solve problems involving increasingly harder fractions to calculate quantities and fractions to divide quantities, including non-unit fractions where the answer is a whole number; solve simple measure and money problems involving fractions and decimals to two decimal places"
  },
  {
    "Uid": "F10_Y5_FRAC",
    "Year": "Year 5",
    "Strand": "Fractions, decimals and percentages",
    "Substrand": "solve problems with fractions and decimals",
    "Ref": "F10",
    "Module": "solve problems involving numbers up to three decimal places"
  },
  {
    "Uid": "F10_Y6_FRAC",
    "Year": "Year 6",
    "Strand": "Fractions, decimals and percentages",
    "Substrand": "solve problems with fractions and decimals",
    "Ref": "F10",
    "Module": "solve problems which require answers to be rounded to specified degrees of accuracy"
  },
  {
    "Uid": "F11_Y1_FRAC",
    "Year": "Year 1",
    "Strand": "Fractions, decimals and percentages",
    "Substrand": "fractions / decimal / percentage equivalence",
    "Ref": "F11",
    "Module": ""
  },
  {
    "Uid": "F11_Y2_FRAC",
    "Year": "Year 2",
    "Strand": "Fractions, decimals and percentages",
    "Substrand": "fractions / decimal / percentage equivalence",
    "Ref": "F11",
    "Module": ""
  },
  {
    "Uid": "F11_Y3_FRAC",
    "Year": "Year 3",
    "Strand": "Fractions, decimals and percentages",
    "Substrand": "fractions / decimal / percentage equivalence",
    "Ref": "F11",
    "Module": ""
  },
  {
    "Uid": "F11_Y4_FRAC",
    "Year": "Year 4",
    "Strand": "Fractions, decimals and percentages",
    "Substrand": "fractions / decimal / percentage equivalence",
    "Ref": "F11",
    "Module": ""
  },
  {
    "Uid": "F11_Y5_FRAC",
    "Year": "Year 5",
    "Strand": "Fractions, decimals and percentages",
    "Substrand": "fractions / decimal / percentage equivalence",
    "Ref": "F11",
    "Module": "recognise the per cent symbol (%) and understand that per cent relates to 'number of parts per hundred'; write percentages as a fraction with denominator hundred, and as a decimal"
  },
  {
    "Uid": "F11_Y6_FRAC",
    "Year": "Year 6",
    "Strand": "Fractions, decimals and percentages",
    "Substrand": "fractions / decimal / percentage equivalence",
    "Ref": "F11",
    "Module": "recall and use equivalences between simple fractions, decimals and percentages, including in different contexts"
  },
  {
    "Uid": "F12_Y1_FRAC",
    "Year": "Year 1",
    "Strand": "Fractions, decimals and percentages",
    "Substrand": "solve problems with percentages",
    "Ref": "F12",
    "Module": ""
  },
  {
    "Uid": "F12_Y2_FRAC",
    "Year": "Year 2",
    "Strand": "Fractions, decimals and percentages",
    "Substrand": "solve problems with percentages",
    "Ref": "F12",
    "Module": ""
  },
  {
    "Uid": "F12_Y3_FRAC",
    "Year": "Year 3",
    "Strand": "Fractions, decimals and percentages",
    "Substrand": "solve problems with percentages",
    "Ref": "F12",
    "Module": ""
  },
  {
    "Uid": "F12_Y4_FRAC",
    "Year": "Year 4",
    "Strand": "Fractions, decimals and percentages",
    "Substrand": "solve problems with percentages",
    "Ref": "F12",
    "Module": ""
  },
  {
    "Uid": "F12_Y5_FRAC",
    "Year": "Year 5",
    "Strand": "Fractions, decimals and percentages",
    "Substrand": "solve problems with percentages",
    "Ref": "F12",
    "Module": "solve problems that require knowing percentage and decimal equivalents of ½, ¼, ⅕, ⅖, ⅘ and those fractions with a denominator of a multiple of 10 or 25"
  },
  {
    "Uid": "F12_Y6_FRAC",
    "Year": "Year 6",
    "Strand": "Fractions, decimals and percentages",
    "Substrand": "solve problems with percentages",
    "Ref": "F12",
    "Module": ""
  },
  {
    "Uid": "R01_Y1_RATIO",
    "Year": "Year 1",
    "Strand": "Ratio and proportion",
    "Substrand": "relative sizes, similarity",
    "Ref": "R1",
    "Module": ""
  },
  {
    "Uid": "R01_Y2_RATIO",
    "Year": "Year 2",
    "Strand": "Ratio and proportion",
    "Substrand": "relative sizes, similarity",
    "Ref": "R1",
    "Module": ""
  },
  {
    "Uid": "R01_Y3_RATIO",
    "Year": "Year 3",
    "Strand": "Ratio and proportion",
    "Substrand": "relative sizes, similarity",
    "Ref": "R1",
    "Module": ""
  },
  {
    "Uid": "R01_Y4_RATIO",
    "Year": "Year 4",
    "Strand": "Ratio and proportion",
    "Substrand": "relative sizes, similarity",
    "Ref": "R1",
    "Module": ""
  },
  {
    "Uid": "R01_Y5_RATIO",
    "Year": "Year 5",
    "Strand": "Ratio and proportion",
    "Substrand": "relative sizes, similarity",
    "Ref": "R1",
    "Module": ""
  },
  {
    "Uid": "R01_Y6_RATIO",
    "Year": "Year 6",
    "Strand": "Ratio and proportion",
    "Substrand": "relative sizes, similarity",
    "Ref": "R1",
    "Module": "solve problems involving the relative sizes of two quantities, where missing values can be found by using integer multiplication and division facts"
  },
  {
    "Uid": "R02_Y1_RATIO",
    "Year": "Year 1",
    "Strand": "Ratio and proportion",
    "Substrand": "use of percentages for comparison",
    "Ref": "R2",
    "Module": ""
  },
  {
    "Uid": "R02_Y2_RATIO",
    "Year": "Year 2",
    "Strand": "Ratio and proportion",
    "Substrand": "use of percentages for comparison",
    "Ref": "R2",
    "Module": ""
  },
  {
    "Uid": "R02_Y3_RATIO",
    "Year": "Year 3",
    "Strand": "Ratio and proportion",
    "Substrand": "use of percentages for comparison",
    "Ref": "R2",
    "Module": ""
  },
  {
    "Uid": "R02_Y4_RATIO",
    "Year": "Year 4",
    "Strand": "Ratio and proportion",
    "Substrand": "use of percentages for comparison",
    "Ref": "R2",
    "Module": ""
  },
  {
    "Uid": "R02_Y5_RATIO",
    "Year": "Year 5",
    "Strand": "Ratio and proportion",
    "Substrand": "use of percentages for comparison",
    "Ref": "R2",
    "Module": ""
  },
  {
    "Uid": "R02_Y6_RATIO",
    "Year": "Year 6",
    "Strand": "Ratio and proportion",
    "Substrand": "use of percentages for comparison",
    "Ref": "R2",
    "Module": "solve problems involving the calculation of percentages [e.g. of measures such as 15% of 360] and the use of percentages for comparison"
  },
  {
    "Uid": "R03_Y1_RATIO",
    "Year": "Year 1",
    "Strand": "Ratio and proportion",
    "Substrand": "scale factors",
    "Ref": "R3",
    "Module": ""
  },
  {
    "Uid": "R03_Y2_RATIO",
    "Year": "Year 2",
    "Strand": "Ratio and proportion",
    "Substrand": "scale factors",
    "Ref": "R3",
    "Module": ""
  },
  {
    "Uid": "R03_Y3_RATIO",
    "Year": "Year 3",
    "Strand": "Ratio and proportion",
    "Substrand": "scale factors",
    "Ref": "R3",
    "Module": ""
  },
  {
    "Uid": "R03_Y4_RATIO",
    "Year": "Year 4",
    "Strand": "Ratio and proportion",
    "Substrand": "scale factors",
    "Ref": "R3",
    "Module": ""
  },
  {
    "Uid": "R03_Y5_RATIO",
    "Year": "Year 5",
    "Strand": "Ratio and proportion",
    "Substrand": "scale factors",
    "Ref": "R3",
    "Module": ""
  },
  {
    "Uid": "R03_Y6_RATIO",
    "Year": "Year 6",
    "Strand": "Ratio and proportion",
    "Substrand": "scale factors",
    "Ref": "R3",
    "Module": "solve problem involving similar shapes where the scale factor is known or can be found"
  },
  {
    "Uid": "R04_Y1_RATIO",
    "Year": "Year 1",
    "Strand": "Ratio and proportion",
    "Substrand": "unequal sharing and grouping",
    "Ref": "R4",
    "Module": ""
  },
  {
    "Uid": "R04_Y2_RATIO",
    "Year": "Year 2",
    "Strand": "Ratio and proportion",
    "Substrand": "unequal sharing and grouping",
    "Ref": "R4",
    "Module": ""
  },
  {
    "Uid": "R04_Y3_RATIO",
    "Year": "Year 3",
    "Strand": "Ratio and proportion",
    "Substrand": "unequal sharing and grouping",
    "Ref": "R4",
    "Module": ""
  },
  {
    "Uid": "R04_Y4_RATIO",
    "Year": "Year 4",
    "Strand": "Ratio and proportion",
    "Substrand": "unequal sharing and grouping",
    "Ref": "R4",
    "Module": ""
  },
  {
    "Uid": "R04_Y5_RATIO",
    "Year": "Year 5",
    "Strand": "Ratio and proportion",
    "Substrand": "unequal sharing and grouping",
    "Ref": "R4",
    "Module": ""
  },
  {
    "Uid": "R04_Y6_RATIO",
    "Year": "Year 6",
    "Strand": "Ratio and proportion",
    "Substrand": "unequal sharing and grouping",
    "Ref": "R4",
    "Module": "solve problems involving unequal sharing and grouping using knowledge of fractions and multiples"
  },
  {
    "Uid": "A01_Y1_ALG",
    "Year": "Year 1",
    "Strand": "Algebra",
    "Substrand": "missing number problems expressed in algebra",
    "Ref": "A1",
    "Module": ""
  },
  {
    "Uid": "A01_Y2_ALG",
    "Year": "Year 2",
    "Strand": "Algebra",
    "Substrand": "missing number problems expressed in algebra",
    "Ref": "A1",
    "Module": ""
  },
  {
    "Uid": "A01_Y3_ALG",
    "Year": "Year 3",
    "Strand": "Algebra",
    "Substrand": "missing number problems expressed in algebra",
    "Ref": "A1",
    "Module": ""
  },
  {
    "Uid": "A01_Y4_ALG",
    "Year": "Year 4",
    "Strand": "Algebra",
    "Substrand": "missing number problems expressed in algebra",
    "Ref": "A1",
    "Module": ""
  },
  {
    "Uid": "A01_Y5_ALG",
    "Year": "Year 5",
    "Strand": "Algebra",
    "Substrand": "missing number problems expressed in algebra",
    "Ref": "A1",
    "Module": ""
  },
  {
    "Uid": "A01_Y6_ALG",
    "Year": "Year 6",
    "Strand": "Algebra",
    "Substrand": "missing number problems expressed in algebra",
    "Ref": "A1",
    "Module": "express missing number problems algebraically"
  },
  {
    "Uid": "A02_Y1_ALG",
    "Year": "Year 1",
    "Strand": "Algebra",
    "Substrand": "simple formulae expressed in words",
    "Ref": "A2",
    "Module": ""
  },
  {
    "Uid": "A02_Y2_ALG",
    "Year": "Year 2",
    "Strand": "Algebra",
    "Substrand": "simple formulae expressed in words",
    "Ref": "A2",
    "Module": ""
  },
  {
    "Uid": "A02_Y3_ALG",
    "Year": "Year 3",
    "Strand": "Algebra",
    "Substrand": "simple formulae expressed in words",
    "Ref": "A2",
    "Module": ""
  },
  {
    "Uid": "A02_Y4_ALG",
    "Year": "Year 4",
    "Strand": "Algebra",
    "Substrand": "simple formulae expressed in words",
    "Ref": "A2",
    "Module": ""
  },
  {
    "Uid": "A02_Y5_ALG",
    "Year": "Year 5",
    "Strand": "Algebra",
    "Substrand": "simple formulae expressed in words",
    "Ref": "A2",
    "Module": ""
  },
  {
    "Uid": "A02_Y6_ALG",
    "Year": "Year 6",
    "Strand": "Algebra",
    "Substrand": "simple formulae expressed in words",
    "Ref": "A2",
    "Module": "use simple formulae"
  },
  {
    "Uid": "A03_Y1_ALG",
    "Year": "Year 1",
    "Strand": "Algebra",
    "Substrand": "generate and describe linear number sequences",
    "Ref": "A3",
    "Module": ""
  },
  {
    "Uid": "A03_Y2_ALG",
    "Year": "Year 2",
    "Strand": "Algebra",
    "Substrand": "generate and describe linear number sequences",
    "Ref": "A3",
    "Module": ""
  },
  {
    "Uid": "A03_Y3_ALG",
    "Year": "Year 3",
    "Strand": "Algebra",
    "Substrand": "generate and describe linear number sequences",
    "Ref": "A3",
    "Module": ""
  },
  {
    "Uid": "A03_Y4_ALG",
    "Year": "Year 4",
    "Strand": "Algebra",
    "Substrand": "generate and describe linear number sequences",
    "Ref": "A3",
    "Module": ""
  },
  {
    "Uid": "A03_Y5_ALG",
    "Year": "Year 5",
    "Strand": "Algebra",
    "Substrand": "generate and describe linear number sequences",
    "Ref": "A3",
    "Module": ""
  },
  {
    "Uid": "A03_Y6_ALG",
    "Year": "Year 6",
    "Strand": "Algebra",
    "Substrand": "generate and describe linear number sequences",
    "Ref": "A3",
    "Module": "generate and describe linear number sequences"
  },
  {
    "Uid": "A04_Y1_ALG",
    "Year": "Year 1",
    "Strand": "Algebra",
    "Substrand": "number sentences involving two unknowns",
    "Ref": "A4",
    "Module": ""
  },
  {
    "Uid": "A04_Y2_ALG",
    "Year": "Year 2",
    "Strand": "Algebra",
    "Substrand": "number sentences involving two unknowns",
    "Ref": "A4",
    "Module": ""
  },
  {
    "Uid": "A04_Y3_ALG",
    "Year": "Year 3",
    "Strand": "Algebra",
    "Substrand": "number sentences involving two unknowns",
    "Ref": "A4",
    "Module": ""
  },
  {
    "Uid": "A04_Y4_ALG",
    "Year": "Year 4",
    "Strand": "Algebra",
    "Substrand": "number sentences involving two unknowns",
    "Ref": "A4",
    "Module": ""
  },
  {
    "Uid": "A04_Y5_ALG",
    "Year": "Year 5",
    "Strand": "Algebra",
    "Substrand": "number sentences involving two unknowns",
    "Ref": "A4",
    "Module": ""
  },
  {
    "Uid": "A04_Y6_ALG",
    "Year": "Year 6",
    "Strand": "Algebra",
    "Substrand": "number sentences involving two unknowns",
    "Ref": "A4",
    "Module": "find pairs of numbers that satisfy an equation with two unknowns"
  },
  {
    "Uid": "A05_Y1_ALG",
    "Year": "Year 1",
    "Strand": "Algebra",
    "Substrand": "enumerate all possibilities of combinations of two variables",
    "Ref": "A5",
    "Module": ""
  },
  {
    "Uid": "A05_Y2_ALG",
    "Year": "Year 2",
    "Strand": "Algebra",
    "Substrand": "enumerate all possibilities of combinations of two variables",
    "Ref": "A5",
    "Module": ""
  },
  {
    "Uid": "A05_Y3_ALG",
    "Year": "Year 3",
    "Strand": "Algebra",
    "Substrand": "enumerate all possibilities of combinations of two variables",
    "Ref": "A5",
    "Module": ""
  },
  {
    "Uid": "A05_Y4_ALG",
    "Year": "Year 4",
    "Strand": "Algebra",
    "Substrand": "enumerate all possibilities of combinations of two variables",
    "Ref": "A5",
    "Module": ""
  },
  {
    "Uid": "A05_Y5_ALG",
    "Year": "Year 5",
    "Strand": "Algebra",
    "Substrand": "enumerate all possibilities of combinations of two variables",
    "Ref": "A5",
    "Module": ""
  },
  {
    "Uid": "A05_Y6_ALG",
    "Year": "Year 6",
    "Strand": "Algebra",
    "Substrand": "enumerate all possibilities of combinations of two variables",
    "Ref": "A5",
    "Module": "enumerate possibilities of combinations of two variables"
  },
  {
    "Uid": "M01_Y1_MEAS",
    "Year": "Year 1",
    "Strand": "Measurement",
    "Substrand": "compare, describe and order measures",
    "Ref": "M1",
    "Module": "compare, describe and solve practical problems for: lengths and heights (e.g. long/short, taller/shorter); mass/weight (e.g. heavy/light, heavier than); capacity and volume (e.g. full/empty, more than/less than); time (e.g. quicker, slower)"
  },
  {
    "Uid": "M01_Y2_MEAS",
    "Year": "Year 2",
    "Strand": "Measurement",
    "Substrand": "compare, describe and order measures",
    "Ref": "M1",
    "Module": "compare and order lengths, mass, volume/capacity and record the results using >, < and ="
  },
  {
    "Uid": "M01_Y3_MEAS",
    "Year": "Year 3",
    "Strand": "Measurement",
    "Substrand": "compare, describe and order measures",
    "Ref": "M1",
    "Module": "compare lengths (m/cm/mm); compare mass (kg/g); compare volume/capacity (l/ml)"
  },
  {
    "Uid": "M01_Y4_MEAS",
    "Year": "Year 4",
    "Strand": "Measurement",
    "Substrand": "compare, describe and order measures",
    "Ref": "M1",
    "Module": "compare different measures, including money in pounds and pence"
  },
  {
    "Uid": "M01_Y5_MEAS",
    "Year": "Year 5",
    "Strand": "Measurement",
    "Substrand": "compare, describe and order measures",
    "Ref": "M1",
    "Module": ""
  },
  {
    "Uid": "M01_Y6_MEAS",
    "Year": "Year 6",
    "Strand": "Measurement",
    "Substrand": "compare, describe and order measures",
    "Ref": "M1",
    "Module": ""
  },
  {
    "Uid": "M02_Y1_MEAS",
    "Year": "Year 1",
    "Strand": "Measurement",
    "Substrand": "estimate, measure and read scales",
    "Ref": "M2",
    "Module": "measure and begin to record: lengths and heights; mass/weight; capacity and volume; time (hours, minutes, seconds)"
  },
  {
    "Uid": "M02_Y2_MEAS",
    "Year": "Year 2",
    "Strand": "Measurement",
    "Substrand": "estimate, measure and read scales",
    "Ref": "M2",
    "Module": "choose and use appropriate standard units to estimate and measure: length/height (m/cm); mass (kg/g); temperature (°C); capacity (litres/ml) to the nearest appropriate unit, using rulers, scales, thermometers and measuring vessels"
  },
  {
    "Uid": "M02_Y3_MEAS",
    "Year": "Year 3",
    "Strand": "Measurement",
    "Substrand": "estimate, measure and read scales",
    "Ref": "M2",
    "Module": "measure lengths (m/cm/mm); measure mass (kg/g); measure volume / capacity (l/ml)"
  },
  {
    "Uid": "M02_Y4_MEAS",
    "Year": "Year 4",
    "Strand": "Measurement",
    "Substrand": "estimate, measure and read scales",
    "Ref": "M2",
    "Module": "estimate different measures, including money in pounds and pence"
  },
  {
    "Uid": "M02_Y5_MEAS",
    "Year": "Year 5",
    "Strand": "Measurement",
    "Substrand": "estimate, measure and read scales",
    "Ref": "M2",
    "Module": ""
  },
  {
    "Uid": "M02_Y6_MEAS",
    "Year": "Year 6",
    "Strand": "Measurement",
    "Substrand": "estimate, measure and read scales",
    "Ref": "M2",
    "Module": ""
  },
  {
    "Uid": "M03_Y1_MEAS",
    "Year": "Year 1",
    "Strand": "Measurement",
    "Substrand": "money",
    "Ref": "M3",
    "Module": "recognise and know the value of different denominations of coins and notes"
  },
  {
    "Uid": "M03_Y2_MEAS",
    "Year": "Year 2",
    "Strand": "Measurement",
    "Substrand": "money",
    "Ref": "M3",
    "Module": "recognise and use symbols for pounds (£) and pence (p); combine amounts to make a particular value; find different combinations of coins that equal the same amounts of money"
  },
  {
    "Uid": "M03_Y3_MEAS",
    "Year": "Year 3",
    "Strand": "Measurement",
    "Substrand": "money",
    "Ref": "M3",
    "Module": "Key stage 1 content domain"
  },
  {
    "Uid": "M03_Y4_MEAS",
    "Year": "Year 4",
    "Strand": "Measurement",
    "Substrand": "money",
    "Ref": "M3",
    "Module": ""
  },
  {
    "Uid": "M03_Y5_MEAS",
    "Year": "Year 5",
    "Strand": "Measurement",
    "Substrand": "money",
    "Ref": "M3",
    "Module": ""
  },
  {
    "Uid": "M03_Y6_MEAS",
    "Year": "Year 6",
    "Strand": "Measurement",
    "Substrand": "money",
    "Ref": "M3",
    "Module": ""
  },
  {
    "Uid": "M04_Y1_MEAS",
    "Year": "Year 1",
    "Strand": "Measurement",
    "Substrand": "telling time, ordering time, duration and units of time",
    "Ref": "M4",
    "Module": "tell the time to the hour and half past the hour and draw the hands on a clock face to show these times; sequence events in chronological order using language (e.g. before, after, next); recognise and use language relating to dates, including days of the week, weeks, months and years"
  },
  {
    "Uid": "M04_Y2_MEAS",
    "Year": "Year 2",
    "Strand": "Measurement",
    "Substrand": "telling time, ordering time, duration and units of time",
    "Ref": "M4",
    "Module": "tell and write the time to five minutes, including quarter past/to the hour and draw the hands on a clock face to show these times; compare and sequence intervals of time; know the number of minutes in an hour and the number of hours in a day"
  },
  {
    "Uid": "M04_Y3_MEAS",
    "Year": "Year 3",
    "Strand": "Measurement",
    "Substrand": "telling time, ordering time, duration and units of time",
    "Ref": "M4",
    "Module": "tell and write the time from an analogue clock; 12-hour clocks; tell and write the time from an analogue clock; 24-hour clocks; tell and write the time from an analogue clock, including using Roman numerals from I to XII; estimate and read time with increasing accuracy to the nearest minute; record and compare time in terms of seconds, minutes and hours; use vocabulary such as o'clock / a.m. / p.m., morning, afternoon, noon and midnight; know the number of seconds in a minute and the number of days in each month, year and leap year; compare durations of events, [e.g. to calculate the time taken by particular events or tasks]"
  },
  {
    "Uid": "M04_Y4_MEAS",
    "Year": "Year 4",
    "Strand": "Measurement",
    "Substrand": "telling time, ordering time, duration and units of time",
    "Ref": "M4",
    "Module": "read, write and convert time between analogue and digital 12-hour clocks; read, write and convert time between analogue and digital 24-hour clocks; solve problems involving converting from hours to minutes; minutes to seconds; years to months; weeks to days"
  },
  {
    "Uid": "M04_Y5_MEAS",
    "Year": "Year 5",
    "Strand": "Measurement",
    "Substrand": "telling time, ordering time, duration and units of time",
    "Ref": "M4",
    "Module": "solve problems involving converting between units of time"
  },
  {
    "Uid": "M04_Y6_MEAS",
    "Year": "Year 6",
    "Strand": "Measurement",
    "Substrand": "telling time, ordering time, duration and units of time",
    "Ref": "M4",
    "Module": ""
  },
  {
    "Uid": "M05_Y1_MEAS",
    "Year": "Year 1",
    "Strand": "Measurement",
    "Substrand": "convert between metric units",
    "Ref": "M5",
    "Module": ""
  },
  {
    "Uid": "M05_Y2_MEAS",
    "Year": "Year 2",
    "Strand": "Measurement",
    "Substrand": "convert between metric units",
    "Ref": "M5",
    "Module": ""
  },
  {
    "Uid": "M05_Y3_MEAS",
    "Year": "Year 3",
    "Strand": "Measurement",
    "Substrand": "convert between metric units",
    "Ref": "M5",
    "Module": ""
  },
  {
    "Uid": "M05_Y4_MEAS",
    "Year": "Year 4",
    "Strand": "Measurement",
    "Substrand": "convert between metric units",
    "Ref": "M5",
    "Module": ""
  },
  {
    "Uid": "M05_Y5_MEAS",
    "Year": "Year 5",
    "Strand": "Measurement",
    "Substrand": "convert between metric units",
    "Ref": "M5",
    "Module": "convert between different units of metric measure [e.g. kilometre and metre; centimetre and metre; centimetre and millimetre; gram and kilogram; litre and millilitre]"
  },
  {
    "Uid": "M05_Y6_MEAS",
    "Year": "Year 6",
    "Strand": "Measurement",
    "Substrand": "convert between metric units",
    "Ref": "M5",
    "Module": ""
  },
  {
    "Uid": "M06_Y1_MEAS",
    "Year": "Year 1",
    "Strand": "Measurement",
    "Substrand": "convert metric / imperial",
    "Ref": "M6",
    "Module": ""
  },
  {
    "Uid": "M06_Y2_MEAS",
    "Year": "Year 2",
    "Strand": "Measurement",
    "Substrand": "convert metric / imperial",
    "Ref": "M6",
    "Module": ""
  },
  {
    "Uid": "M06_Y3_MEAS",
    "Year": "Year 3",
    "Strand": "Measurement",
    "Substrand": "convert metric / imperial",
    "Ref": "M6",
    "Module": ""
  },
  {
    "Uid": "M06_Y4_MEAS",
    "Year": "Year 4",
    "Strand": "Measurement",
    "Substrand": "convert metric / imperial",
    "Ref": "M6",
    "Module": "convert between different units of measurement [e.g. kilometre to metre; hour to minute]"
  },
  {
    "Uid": "M06_Y5_MEAS",
    "Year": "Year 5",
    "Strand": "Measurement",
    "Substrand": "convert metric / imperial",
    "Ref": "M6",
    "Module": "understand and use approximate equivalences between metric units and common imperial units such as inches, pounds and pints"
  },
  {
    "Uid": "M06_Y6_MEAS",
    "Year": "Year 6",
    "Strand": "Measurement",
    "Substrand": "convert metric / imperial",
    "Ref": "M6",
    "Module": "use, read, write and convert between standard units, converting measurements of length, mass, volume and time from a smaller unit of measure to a larger unit, and vice versa, using decimal notation of up to three decimal places; convert between miles and kilometres"
  },
  {
    "Uid": "M07_Y1_MEAS",
    "Year": "Year 1",
    "Strand": "Measurement",
    "Substrand": "perimeter, area",
    "Ref": "M7",
    "Module": ""
  },
  {
    "Uid": "M07_Y2_MEAS",
    "Year": "Year 2",
    "Strand": "Measurement",
    "Substrand": "perimeter, area",
    "Ref": "M7",
    "Module": ""
  },
  {
    "Uid": "M07_Y3_MEAS",
    "Year": "Year 3",
    "Strand": "Measurement",
    "Substrand": "perimeter, area",
    "Ref": "M7",
    "Module": "measure the perimeter of simple 2-D shapes"
  },
  {
    "Uid": "M07_Y4_MEAS",
    "Year": "Year 4",
    "Strand": "Measurement",
    "Substrand": "perimeter, area",
    "Ref": "M7",
    "Module": "measure and calculate the perimeter of a rectilinear figure (including squares) in centimetres and metres; find the area of rectilinear shapes by counting squares"
  },
  {
    "Uid": "M07_Y5_MEAS",
    "Year": "Year 5",
    "Strand": "Measurement",
    "Substrand": "perimeter, area",
    "Ref": "M7",
    "Module": "measure and calculate the perimeter of composite rectilinear shapes in centimetres and metres; calculate and compare the area of rectangles (including squares), and including using standard units, square centimetres (cm²) and square metres (m²) and estimate the area of irregular shapes"
  },
  {
    "Uid": "M07_Y6_MEAS",
    "Year": "Year 6",
    "Strand": "Measurement",
    "Substrand": "perimeter, area",
    "Ref": "M7",
    "Module": "recognise that shapes with the same areas can have different perimeters and vice versa; calculate the area of parallelograms and triangles; recognise when it is possible to use the formulae for the area of shapes"
  },
  {
    "Uid": "M08_Y1_MEAS",
    "Year": "Year 1",
    "Strand": "Measurement",
    "Substrand": "volume",
    "Ref": "M8",
    "Module": ""
  },
  {
    "Uid": "M08_Y2_MEAS",
    "Year": "Year 2",
    "Strand": "Measurement",
    "Substrand": "volume",
    "Ref": "M8",
    "Module": ""
  },
  {
    "Uid": "M08_Y3_MEAS",
    "Year": "Year 3",
    "Strand": "Measurement",
    "Substrand": "volume",
    "Ref": "M8",
    "Module": ""
  },
  {
    "Uid": "M08_Y4_MEAS",
    "Year": "Year 4",
    "Strand": "Measurement",
    "Substrand": "volume",
    "Ref": "M8",
    "Module": ""
  },
  {
    "Uid": "M08_Y5_MEAS",
    "Year": "Year 5",
    "Strand": "Measurement",
    "Substrand": "volume",
    "Ref": "M8",
    "Module": "estimate volume [e.g. using 1 cm³ blocks to build cuboids (including cubes)] and capacity [e.g. using water]"
  },
  {
    "Uid": "M08_Y6_MEAS",
    "Year": "Year 6",
    "Strand": "Measurement",
    "Substrand": "volume",
    "Ref": "M8",
    "Module": "calculate, estimate and compare volume of cubes and cuboids using standard units, including centimetre cubed (cm³) and cubic metres (m³), and extending to other units [e.g. mm³ and km³]; recognise when it is possible to use the formulae for the volume of shapes"
  },
  {
    "Uid": "M09_Y1_MEAS",
    "Year": "Year 1",
    "Strand": "Measurement",
    "Substrand": "solve problems (a, money; b, length; c, mass / weight; d, capacity / volume)",
    "Ref": "M9",
    "Module": ""
  },
  {
    "Uid": "M09_Y2_MEAS",
    "Year": "Year 2",
    "Strand": "Measurement",
    "Substrand": "solve problems (a, money; b, length; c, mass / weight; d, capacity / volume)",
    "Ref": "M9",
    "Module": "solve simple problems in a practical context involving addition and subtraction of money of the same unit, including giving change"
  },
  {
    "Uid": "M09_Y3_MEAS",
    "Year": "Year 3",
    "Strand": "Measurement",
    "Substrand": "solve problems (a, money; b, length; c, mass / weight; d, capacity / volume)",
    "Ref": "M9",
    "Module": "add and subtract amounts of money to give change, using both pounds (£) and pence (p) in practical contexts; add and subtract lengths (m/cm/mm); add and subtract mass (kg/g); add and subtract volume / capacity (l/ml)"
  },
  {
    "Uid": "M09_Y4_MEAS",
    "Year": "Year 4",
    "Strand": "Measurement",
    "Substrand": "solve problems (a, money; b, length; c, mass / weight; d, capacity / volume)",
    "Ref": "M9",
    "Module": "calculate different measures, including money in pounds and pence"
  },
  {
    "Uid": "M09_Y5_MEAS",
    "Year": "Year 5",
    "Strand": "Measurement",
    "Substrand": "solve problems (a, money; b, length; c, mass / weight; d, capacity / volume)",
    "Ref": "M9",
    "Module": "use all four operations to solve problems involving measures [money] using decimal notation, including scaling; use all four operations to solve problems involving measure [e.g. length] using decimal notation, including scaling; use all four operations to solve problems involving measure [e.g. mass] using decimal notation, including scaling; use all four operations to solve problems involving measure [e.g. volume] using decimal notation, including scaling"
  },
  {
    "Uid": "M09_Y6_MEAS",
    "Year": "Year 6",
    "Strand": "Measurement",
    "Substrand": "solve problems (a, money; b, length; c, mass / weight; d, capacity / volume)",
    "Ref": "M9",
    "Module": "solve problems involving the calculation and conversion of units of measure, using decimal notation up to three decimal places where appropriate"
  },
  {
    "Uid": "G01_Y1_GEO",
    "Year": "Year 1",
    "Strand": "Geometry – properties of shapes",
    "Substrand": "recognise and name common shapes",
    "Ref": "G1",
    "Module": "recognise and name common 2-D shapes (e.g. rectangles, squares, circles, triangles); recognise and name common 3-D shapes (e.g. cuboids, cubes, pyramids, spheres)"
  },
  {
    "Uid": "G01_Y2_GEO",
    "Year": "Year 2",
    "Strand": "Geometry – properties of shapes",
    "Substrand": "recognise and name common shapes",
    "Ref": "G1",
    "Module": "compare and sort common 2-D and 3-D shapes and everyday objects"
  },
  {
    "Uid": "G01_Y3_GEO",
    "Year": "Year 3",
    "Strand": "Geometry – properties of shapes",
    "Substrand": "recognise and name common shapes",
    "Ref": "G1",
    "Module": "Within key stage 1 content domain"
  },
  {
    "Uid": "G01_Y4_GEO",
    "Year": "Year 4",
    "Strand": "Geometry – properties of shapes",
    "Substrand": "recognise and name common shapes",
    "Ref": "G1",
    "Module": ""
  },
  {
    "Uid": "G01_Y5_GEO",
    "Year": "Year 5",
    "Strand": "Geometry – properties of shapes",
    "Substrand": "recognise and name common shapes",
    "Ref": "G1",
    "Module": ""
  },
  {
    "Uid": "G01_Y6_GEO",
    "Year": "Year 6",
    "Strand": "Geometry – properties of shapes",
    "Substrand": "recognise and name common shapes",
    "Ref": "G1",
    "Module": ""
  },
  {
    "Uid": "G02_Y1_GEO",
    "Year": "Year 1",
    "Strand": "Geometry – properties of shapes",
    "Substrand": "describe properties and classify shapes",
    "Ref": "G2",
    "Module": ""
  },
  {
    "Uid": "G02_Y2_GEO",
    "Year": "Year 2",
    "Strand": "Geometry – properties of shapes",
    "Substrand": "describe properties and classify shapes",
    "Ref": "G2",
    "Module": "identify and describe the properties of 2-D shapes, including the number of sides and line symmetry in a vertical line; identify and describe the properties of 3-D shapes, including the number of edges, vertices and faces"
  },
  {
    "Uid": "G02_Y3_GEO",
    "Year": "Year 3",
    "Strand": "Geometry – properties of shapes",
    "Substrand": "describe properties and classify shapes",
    "Ref": "G2",
    "Module": "identify horizontal, vertical lines and pairs of perpendicular and parallel lines"
  },
  {
    "Uid": "G02_Y4_GEO",
    "Year": "Year 4",
    "Strand": "Geometry – properties of shapes",
    "Substrand": "describe properties and classify shapes",
    "Ref": "G2",
    "Module": "compare and classify geometric shapes, including quadrilaterals and triangles based on their properties and sizes; identify lines of symmetry in 2-D shapes presented in different orientations; complete a simple symmetric figure with respect to a specific line of symmetry"
  },
  {
    "Uid": "G02_Y5_GEO",
    "Year": "Year 5",
    "Strand": "Geometry – properties of shapes",
    "Substrand": "describe properties and classify shapes",
    "Ref": "G2",
    "Module": "use the properties of rectangles to deduce related facts and find missing lengths and angles; distinguish between regular and irregular polygons based on reasoning about equal sides and angles"
  },
  {
    "Uid": "G02_Y6_GEO",
    "Year": "Year 6",
    "Strand": "Geometry – properties of shapes",
    "Substrand": "describe properties and classify shapes",
    "Ref": "G2",
    "Module": "compare and classify geometric shapes based on their properties and sizes; describe simple 3-D shapes"
  },
  {
    "Uid": "G03_Y1_GEO",
    "Year": "Year 1",
    "Strand": "Geometry – properties of shapes",
    "Substrand": "draw and make shapes and relate 2-D to 3-D shapes (including nets)",
    "Ref": "G3",
    "Module": ""
  },
  {
    "Uid": "G03_Y2_GEO",
    "Year": "Year 2",
    "Strand": "Geometry – properties of shapes",
    "Substrand": "draw and make shapes and relate 2-D to 3-D shapes (including nets)",
    "Ref": "G3",
    "Module": "identify 2-D shapes on the surface of 3-D shapes (e.g. a circle on a cylinder and a triangle on a pyramid)"
  },
  {
    "Uid": "G03_Y3_GEO",
    "Year": "Year 3",
    "Strand": "Geometry – properties of shapes",
    "Substrand": "draw and make shapes and relate 2-D to 3-D shapes (including nets)",
    "Ref": "G3",
    "Module": "draw 2-D shapes; make 3-D shapes using modelling materials; recognise 3-D shapes in different orientations and describe them"
  },
  {
    "Uid": "G03_Y4_GEO",
    "Year": "Year 4",
    "Strand": "Geometry – properties of shapes",
    "Substrand": "draw and make shapes and relate 2-D to 3-D shapes (including nets)",
    "Ref": "G3",
    "Module": ""
  },
  {
    "Uid": "G03_Y5_GEO",
    "Year": "Year 5",
    "Strand": "Geometry – properties of shapes",
    "Substrand": "draw and make shapes and relate 2-D to 3-D shapes (including nets)",
    "Ref": "G3",
    "Module": "identify 3-D shapes including cubes and other cuboids, from 2-D representations"
  },
  {
    "Uid": "G03_Y6_GEO",
    "Year": "Year 6",
    "Strand": "Geometry – properties of shapes",
    "Substrand": "draw and make shapes and relate 2-D to 3-D shapes (including nets)",
    "Ref": "G3",
    "Module": "draw 2-D shapes using given dimensions and angles; recognise and build simple 3-D shapes, including making nets"
  },
  {
    "Uid": "G04_Y1_GEO",
    "Year": "Year 1",
    "Strand": "Geometry – properties of shapes",
    "Substrand": "angles – measuring and properties",
    "Ref": "G4",
    "Module": ""
  },
  {
    "Uid": "G04_Y2_GEO",
    "Year": "Year 2",
    "Strand": "Geometry – properties of shapes",
    "Substrand": "angles – measuring and properties",
    "Ref": "G4",
    "Module": ""
  },
  {
    "Uid": "G04_Y3_GEO",
    "Year": "Year 3",
    "Strand": "Geometry – properties of shapes",
    "Substrand": "angles – measuring and properties",
    "Ref": "G4",
    "Module": "recognise that angles are a property of shape or a description of a turn; identify right angles, recognise that two right angles make a half-turn, three make three quarters of a turn and four a complete turn; identify whether angles are greater than or less than a right angle"
  },
  {
    "Uid": "G04_Y4_GEO",
    "Year": "Year 4",
    "Strand": "Geometry – properties of shapes",
    "Substrand": "angles – measuring and properties",
    "Ref": "G4",
    "Module": "identify acute and obtuse angles and compare and order angles up to two right angles by size"
  },
  {
    "Uid": "G04_Y5_GEO",
    "Year": "Year 5",
    "Strand": "Geometry – properties of shapes",
    "Substrand": "angles – measuring and properties",
    "Ref": "G4",
    "Module": "know angles are measured in degrees: estimate and compare acute, obtuse and reflex angles; identify: angles at a point and one whole turn (total 360°), angles at a point on a straight line and ½ a turn (total 180°), other multiples of 90°; draw given angles and measure them in degrees (°)"
  },
  {
    "Uid": "G04_Y6_GEO",
    "Year": "Year 6",
    "Strand": "Geometry – properties of shapes",
    "Substrand": "angles – measuring and properties",
    "Ref": "G4",
    "Module": "find unknown angles in any triangles, quadrilaterals and regular polygons; recognise angles where they meet at a point, are on a straight line, or are vertically opposite, and find missing angles"
  },
  {
    "Uid": "G05_Y1_GEO",
    "Year": "Year 1",
    "Strand": "Geometry – properties of shapes",
    "Substrand": "circles",
    "Ref": "G5",
    "Module": ""
  },
  {
    "Uid": "G05_Y2_GEO",
    "Year": "Year 2",
    "Strand": "Geometry – properties of shapes",
    "Substrand": "circles",
    "Ref": "G5",
    "Module": ""
  },
  {
    "Uid": "G05_Y3_GEO",
    "Year": "Year 3",
    "Strand": "Geometry – properties of shapes",
    "Substrand": "circles",
    "Ref": "G5",
    "Module": ""
  },
  {
    "Uid": "G05_Y4_GEO",
    "Year": "Year 4",
    "Strand": "Geometry – properties of shapes",
    "Substrand": "circles",
    "Ref": "G5",
    "Module": ""
  },
  {
    "Uid": "G05_Y5_GEO",
    "Year": "Year 5",
    "Strand": "Geometry – properties of shapes",
    "Substrand": "circles",
    "Ref": "G5",
    "Module": ""
  },
  {
    "Uid": "G05_Y6_GEO",
    "Year": "Year 6",
    "Strand": "Geometry – properties of shapes",
    "Substrand": "circles",
    "Ref": "G5",
    "Module": "illustrate and name parts of circles, including radius, diameter and circumference and know that the diameter is twice the radius"
  },
  {
    "Uid": "P01_Y1_POS",
    "Year": "Year 1",
    "Strand": "Geometry - position and direction",
    "Substrand": "patterns",
    "Ref": "P1",
    "Module": ""
  },
  {
    "Uid": "P01_Y2_POS",
    "Year": "Year 2",
    "Strand": "Geometry - position and direction",
    "Substrand": "patterns",
    "Ref": "P1",
    "Module": "order and arrange combinations of mathematical objects in patterns and sequences"
  },
  {
    "Uid": "P01_Y3_POS",
    "Year": "Year 3",
    "Strand": "Geometry - position and direction",
    "Substrand": "patterns",
    "Ref": "P1",
    "Module": "Within key stage 1 content domain"
  },
  {
    "Uid": "P01_Y4_POS",
    "Year": "Year 4",
    "Strand": "Geometry - position and direction",
    "Substrand": "patterns",
    "Ref": "P1",
    "Module": ""
  },
  {
    "Uid": "P01_Y5_POS",
    "Year": "Year 5",
    "Strand": "Geometry - position and direction",
    "Substrand": "patterns",
    "Ref": "P1",
    "Module": ""
  },
  {
    "Uid": "P01_Y6_POS",
    "Year": "Year 6",
    "Strand": "Geometry - position and direction",
    "Substrand": "patterns",
    "Ref": "P1",
    "Module": ""
  },
  {
    "Uid": "P02_Y1_POS",
    "Year": "Year 1",
    "Strand": "Geometry - position and direction",
    "Substrand": "describe position, direction and movement",
    "Ref": "P2",
    "Module": "describe position, direction and movement, including half, quarter and three-quarter turns"
  },
  {
    "Uid": "P02_Y2_POS",
    "Year": "Year 2",
    "Strand": "Geometry - position and direction",
    "Substrand": "describe position, direction and movement",
    "Ref": "P2",
    "Module": "use mathematical vocabulary to describe position, direction and movement, including movement in a straight line and distinguishing between rotation as a turn and in terms of right angles for quarter, half and three-quarter turns (clockwise and anti-clockwise)"
  },
  {
    "Uid": "P02_Y3_POS",
    "Year": "Year 3",
    "Strand": "Geometry - position and direction",
    "Substrand": "describe position, direction and movement",
    "Ref": "P2",
    "Module": ""
  },
  {
    "Uid": "P02_Y4_POS",
    "Year": "Year 4",
    "Strand": "Geometry - position and direction",
    "Substrand": "describe position, direction and movement",
    "Ref": "P2",
    "Module": "describe movements between positions as translations of a given unit to the left / right and up / down"
  },
  {
    "Uid": "P02_Y5_POS",
    "Year": "Year 5",
    "Strand": "Geometry - position and direction",
    "Substrand": "describe position, direction and movement",
    "Ref": "P2",
    "Module": "identify, describe and represent the position of a shape following a reflection or translation, using the appropriate language, and know that the shape has not changed"
  },
  {
    "Uid": "P02_Y6_POS",
    "Year": "Year 6",
    "Strand": "Geometry - position and direction",
    "Substrand": "describe position, direction and movement",
    "Ref": "P2",
    "Module": "draw and translate simple shapes on the co-ordinate plane, and reflect them in the axes"
  },
  {
    "Uid": "P03_Y1_POS",
    "Year": "Year 1",
    "Strand": "Geometry - position and direction",
    "Substrand": "co-ordinates",
    "Ref": "P3",
    "Module": ""
  },
  {
    "Uid": "P03_Y2_POS",
    "Year": "Year 2",
    "Strand": "Geometry - position and direction",
    "Substrand": "co-ordinates",
    "Ref": "P3",
    "Module": ""
  },
  {
    "Uid": "P03_Y3_POS",
    "Year": "Year 3",
    "Strand": "Geometry - position and direction",
    "Substrand": "co-ordinates",
    "Ref": "P3",
    "Module": ""
  },
  {
    "Uid": "P03_Y4_POS",
    "Year": "Year 4",
    "Strand": "Geometry - position and direction",
    "Substrand": "co-ordinates",
    "Ref": "P3",
    "Module": "describe positions on a 2-D grid as co-ordinates in the first quadrant; plot specified points and draw sides to complete a given polygon"
  },
  {
    "Uid": "P03_Y5_POS",
    "Year": "Year 5",
    "Strand": "Geometry - position and direction",
    "Substrand": "co-ordinates",
    "Ref": "P3",
    "Module": ""
  },
  {
    "Uid": "P03_Y6_POS",
    "Year": "Year 6",
    "Strand": "Geometry - position and direction",
    "Substrand": "co-ordinates",
    "Ref": "P3",
    "Module": "describe positions on the full co-ordinate grid (all four quadrants)"
  },
  {
    "Uid": "S01_Y1_STAT",
    "Year": "Year 1",
    "Strand": "Statistics",
    "Substrand": "interpret and represent data",
    "Ref": "S1",
    "Module": ""
  },
  {
    "Uid": "S01_Y2_STAT",
    "Year": "Year 2",
    "Strand": "Statistics",
    "Substrand": "interpret and represent data",
    "Ref": "S1",
    "Module": "interpret and construct simple pictograms, tally charts, block diagrams and simple tables"
  },
  {
    "Uid": "S01_Y3_STAT",
    "Year": "Year 3",
    "Strand": "Statistics",
    "Substrand": "interpret and represent data",
    "Ref": "S1",
    "Module": "interpret and present data using bar charts, pictograms and tables"
  },
  {
    "Uid": "S01_Y4_STAT",
    "Year": "Year 4",
    "Strand": "Statistics",
    "Substrand": "interpret and represent data",
    "Ref": "S1",
    "Module": "interpret and present discrete and continuous data using appropriate graphical methods, including bar charts and time graphs"
  },
  {
    "Uid": "S01_Y5_STAT",
    "Year": "Year 5",
    "Strand": "Statistics",
    "Substrand": "interpret and represent data",
    "Ref": "S1",
    "Module": "complete, read and interpret information in tables, including timetables"
  },
  {
    "Uid": "S01_Y6_STAT",
    "Year": "Year 6",
    "Strand": "Statistics",
    "Substrand": "interpret and represent data",
    "Ref": "S1",
    "Module": "interpret and construct pie charts and line graphs and use these to solve problems"
  },
  {
    "Uid": "S02_Y1_STAT",
    "Year": "Year 1",
    "Strand": "Statistics",
    "Substrand": "solve problems involving data",
    "Ref": "S2",
    "Module": ""
  },
  {
    "Uid": "S02_Y2_STAT",
    "Year": "Year 2",
    "Strand": "Statistics",
    "Substrand": "solve problems involving data",
    "Ref": "S2",
    "Module": "ask and answer simple questions by counting the number of objects in each category and sorting the categories by quantity; ask and answer questions about totalling and comparing categorical data"
  },
  {
    "Uid": "S02_Y3_STAT",
    "Year": "Year 3",
    "Strand": "Statistics",
    "Substrand": "solve problems involving data",
    "Ref": "S2",
    "Module": "solve one-step and two-step questions [e.g. 'How many more?' and 'How many fewer?'] using information presented in scaled bar charts, pictograms and tables"
  },
  {
    "Uid": "S02_Y4_STAT",
    "Year": "Year 4",
    "Strand": "Statistics",
    "Substrand": "solve problems involving data",
    "Ref": "S2",
    "Module": "solve comparison, sum and difference problems using information presented in bar charts, pictograms, tables and other graphs"
  },
  {
    "Uid": "S02_Y5_STAT",
    "Year": "Year 5",
    "Strand": "Statistics",
    "Substrand": "solve problems involving data",
    "Ref": "S2",
    "Module": "solve comparison, sum and difference problems using information presented in a line graph"
  },
  {
    "Uid": "S02_Y6_STAT",
    "Year": "Year 6",
    "Strand": "Statistics",
    "Substrand": "solve problems involving data",
    "Ref": "S2",
    "Module": ""
  },
  {
    "Uid": "S03_Y1_STAT",
    "Year": "Year 1",
    "Strand": "Statistics",
    "Substrand": "mean average",
    "Ref": "S3",
    "Module": ""
  },
  {
    "Uid": "S03_Y2_STAT",
    "Year": "Year 2",
    "Strand": "Statistics",
    "Substrand": "mean average",
    "Ref": "S3",
    "Module": ""
  },
  {
    "Uid": "S03_Y3_STAT",
    "Year": "Year 3",
    "Strand": "Statistics",
    "Substrand": "mean average",
    "Ref": "S3",
    "Module": ""
  },
  {
    "Uid": "S03_Y4_STAT",
    "Year": "Year 4",
    "Strand": "Statistics",
    "Substrand": "mean average",
    "Ref": "S3",
    "Module": ""
  },
  {
    "Uid": "S03_Y5_STAT",
    "Year": "Year 5",
    "Strand": "Statistics",
    "Substrand": "mean average",
    "Ref": "S3",
    "Module": ""
  },
  {
    "Uid": "S03_Y6_STAT",
    "Year": "Year 6",
    "Strand": "Statistics",
    "Substrand": "mean average",
    "Ref": "S3",
    "Module": "calculate and interpret the mean as an average"
  }
]
